ovos_vad_plugin_noise/__init__.py
ovos_vad_plugin_noise/silence.py
ovos_vad_plugin_noise/version.py
ovos_vad_plugin_noise-0.1.2.dist-info/LICENSE
ovos_vad_plugin_noise-0.1.2.dist-info/METADATA
ovos_vad_plugin_noise-0.1.2.dist-info/WHEEL
ovos_vad_plugin_noise-0.1.2.dist-info/entry_points.txt
ovos_vad_plugin_noise-0.1.2.dist-info/top_level.txt
ovos_vad_plugin_noise-0.1.2.dist-info/zip-safe
ovos_vad_plugin_noise-0.1.2.dist-info/RECORD
