Metadata-Version: 2.1
Name: ovos-vad-plugin-noise
Version: 0.1.2
Summary: noise ratio VAD plugin for OpenVoiceOS
Home-page: https://github.com/OpenVoiceOS/ovos-vad-plugin-noise
Author: JarbasAi
Author-email: jarbasai@mailfence.com
License: Apache-2.0
Keywords: mycroft plugin VAD OVOS OpenVoiceOS
Classifier: Development Status :: 3 - Alpha
Classifier: Intended Audience :: Developers
Classifier: Topic :: Text Processing :: Linguistic
Classifier: License :: OSI Approved :: Apache Software License
Classifier: Programming Language :: Python :: 2
Classifier: Programming Language :: Python :: 2.7
Classifier: Programming Language :: Python :: 3
Classifier: Programming Language :: Python :: 3.0
Classifier: Programming Language :: Python :: 3.1
Classifier: Programming Language :: Python :: 3.2
Classifier: Programming Language :: Python :: 3.3
Classifier: Programming Language :: Python :: 3.4
Classifier: Programming Language :: Python :: 3.5
Classifier: Programming Language :: Python :: 3.6
License-File: LICENSE
Requires-Dist: ovos-plugin-manager<2.0.0,>=0.0.11
